desmod/__init__.py
desmod/component.py
desmod/config.py
desmod/dot.py
desmod/pool.py
desmod/probe.py
desmod/progress.py
desmod/py.typed
desmod/queue.py
desmod/simulation.py
desmod/timescale.py
desmod/tracer.py
desmod/util.py
desmod-0.6.1.dist-info/LICENSE.txt
desmod-0.6.1.dist-info/METADATA
desmod-0.6.1.dist-info/WHEEL
desmod-0.6.1.dist-info/top_level.txt
desmod-0.6.1.dist-info/RECORD
