Metadata-Version: 2.1
Name: desmod
Version: 0.6.1
Summary: Discrete Event Simulation Modeling using SimPy
Home-page: https://desmod.readthedocs.io/
Author: Peter Grayson
Author-email: pete@jpgrayson.net
License: MIT
Download-URL: https://github.com/SanDisk-Open-Source/desmod
Platform: UNKNOWN
Classifier: Development Status :: 4 - Beta
Classifier: Environment :: Console
Classifier: Intended Audience :: Developers
Classifier: Intended Audience :: Education
Classifier: Intended Audience :: Science/Research
Classifier: License :: OSI Approved :: MIT License
Classifier: Natural Language :: English
Classifier: Operating System :: OS Independent
Classifier: Programming Language :: Python
Classifier: Programming Language :: Python :: 3
Classifier: Programming Language :: Python :: 3.6
Classifier: Programming Language :: Python :: 3.7
Classifier: Programming Language :: Python :: 3.8
Classifier: Programming Language :: Python :: Implementation :: CPython
Classifier: Programming Language :: Python :: Implementation :: PyPy
Classifier: Topic :: Scientific/Engineering
Requires-Python: >= 3.6
Requires-Dist: simpy (>=4)
Requires-Dist: pyvcd
Requires-Dist: PyYAML
